PrimoPabloCueli/__init__.py
primoPabloCueli-1.0.dist-info/LICENSE
primoPabloCueli-1.0.dist-info/METADATA
primoPabloCueli-1.0.dist-info/WHEEL
primoPabloCueli-1.0.dist-info/top_level.txt
primoPabloCueli-1.0.dist-info/RECORD
