Metadata-Version: 2.1
Name: primoPabloCueli
Version: 1.0
Summary: A tool to know if a number is prime.
Home-page: UNKNOWN
Author: Pablo Cueli
Author-email: p.cueli9@gmail.com
License: GNU GPLv3
Keywords: prime
Platform: UNKNOWN
Classifier: Development Status :: 4 - Beta
Classifier: Intended Audience :: Developers
Classifier: Topic :: Utilities
Classifier: License :: OSI Approved :: GNU General Public License v3 (GPLv3)
Classifier: Programming Language :: Python :: 3
Classifier: Operating System :: OS Independent
License-File: LICENSE
